virtualmin_dns_authenticator/__init__.py
virtualmin_dns_authenticator/authenticator.py
virtualmin_dns_authenticator-1.0.0.dist-info/METADATA
virtualmin_dns_authenticator-1.0.0.dist-info/WHEEL
virtualmin_dns_authenticator-1.0.0.dist-info/entry_points.txt
virtualmin_dns_authenticator-1.0.0.dist-info/top_level.txt
virtualmin_dns_authenticator-1.0.0.dist-info/RECORD
